{"0_256_3": {"xmlName": "RMS_GPS_Msg_MsgDef", "Name": "GpsStatusReqRsp", "Messages": {"1570618369.698322": [{"name": "GpsInterfaceState", "enumType": "E1_GPS_STATE", "type": "U1", "default": "GPS_OFFLINE", "value": 0, "members": {"GPS_OFFLINE": "0x00", "GPS_SETUP": "0x22", "GPS_OPERATIONAL": "0x25"}}, {"name": "GpsInterfaceMqttId", "type": "CH", "default": "0", "value": "BR12", "count": 48}, {"name": "GpsHighLevelStatus", "enumType": "E1_GPS_STATUS", "type": "U1", "default": "GPS_UNKNOWN", "value": 3, "members": {"GPS_PASS": "1", "GPS_DEGRADED": "2", "GPS_FAIL": "3", "GPS_UNKNOWN": "4"}}, {"name": "GpsLinkStatus", "type": "sGPS_LinkStatus", "members": [{"name": "BoundToUdpPort", "enumType": "E1_GPS_BOOLEAN", "type": "U1", "default": "0", "value": 1, "members": {"GPS_FALSE": "0", "GPS_TRUE": "1"}}, {"name": "MsgId29Present", "enumType": "E1_GPS_BOOLEAN", "type": "U1", "default": "0", "value": 0, "members": {"GPS_FALSE": "0", "GPS_TRUE": "1"}}, {"name": "MsgId23Present", "enumType": "E1_GPS_BOOLEAN", "type": "U1", "default": "0", "value": 0, "members": {"GPS_FALSE": "0", "GPS_TRUE": "1"}}]}, {"name": "GpsTime", "type": "sGPS_Time", "members": [{"name": "TimeValid", "enumType": "E1_GPS_BOOLEAN", "type": "U1", "default": "0", "value": 0, "members": {"GPS_FALSE": "0", "GPS_TRUE": "1"}}, {"name": "UnixTimestampSeconds", "type": "U4", "default": "0", "value": 0}, {"name": "Microseconds", "type": "U4", "default": "0", "value": 0}]}, {"name": "GpsPosition", "type": "sGPS_Position", "members": [{"name": "PositionValid", "enumType": "E1_GPS_BOOLEAN", "type": "U1", "default": "0", "value": 0, "members": {"GPS_FALSE": "0", "GPS_TRUE": "1"}}, {"name": "TypeOfFix", "enumType": "E1_GPS_GNSS_FIX_STATUS", "type": "U1", "default": "0", "value": 0, "members": {"GPS_NO_FIX": "0", "GPS_2D_FIX": "1", "GPS_3D_FIX": "2", "GPS_SBAS_GNSS_FIX": "3", "GPS_DIFFERENTIAL_GNSS_FIX": "4", "GPS_OMNISTAR_GNSS_FIX": "5", "GPS_RTK_FLOAT_GNSS_FIX": "6", "GPS_RTK_FIXED_GNSS_FIX": "7"}}, {"name": "HightMeters", "type": "F4", "default": "0", "value": 0.0}, {"name": "LatitudeDecimalDegrees", "type": "F4", "default": "0", "value": 0.0}, {"name": "LongitudeDecimalDegrees", "type": "F4", "default": "0", "value": 0.0}]}, {"name": "GpsHeading", "type": "sGPS_Heading", "members": [{"name": "HeadingValid", "enumType": "E1_GPS_BOOLEAN", "type": "U1", "default": "0", "value": 0, "members": {"GPS_FALSE": "0", "GPS_TRUE": "1"}}, {"name": "HeadingDegrees", "type": "F4", "default": "0", "value": 0.0}, {"name": "HeadingStandardDeviation", "type": "F4", "default": "0", "value": 0.0}]}, {"name": "GpsModuleStatus", "type": "sGPS_ModuleStatus", "members": [{"name": "SystemFailure", "enumType": "E1_GPS_BOOLEAN", "type": "U1", "default": "0", "value": 0, "members": {"GPS_FALSE": "0", "GPS_TRUE": "1"}}, {"name": "AccelerometerSensorFailure", "enumType": "E1_GPS_BOOLEAN", "type": "U1", "default": "0", "value": 0, "members": {"GPS_FALSE": "0", "GPS_TRUE": "1"}}, {"name": "GyroscopeSensorFailure", "enumType": "E1_GPS_BOOLEAN", "type": "U1", "default": "0", "value": 0, "members": {"GPS_FALSE": "0", "GPS_TRUE": "1"}}, {"name": "MagnetometerSensorFailure", "enumType": "E1_GPS_BOOLEAN", "type": "U1", "default": "0", "value": 0, "members": {"GPS_FALSE": "0", "GPS_TRUE": "1"}}, {"name": "SecondaryGnssFailure", "enumType": "E1_GPS_BOOLEAN", "type": "U1", "default": "0", "value": 0, "members": {"GPS_FALSE": "0", "GPS_TRUE": "1"}}, {"name": "PrimaryGnssFailure", "enumType": "E1_GPS_BOOLEAN", "type": "U1", "default": "0", "value": 0, "members": {"GPS_FALSE": "0", "GPS_TRUE": "1"}}, {"name": "AccelerometerOverRange", "enumType": "E1_GPS_BOOLEAN", "type": "U1", "default": "0", "value": 0, "members": {"GPS_FALSE": "0", "GPS_TRUE": "1"}}, {"name": "GyroscopeOverRange", "enumType": "E1_GPS_BOOLEAN", "type": "U1", "default": "0", "value": 0, "members": {"GPS_FALSE": "0", "GPS_TRUE": "1"}}, {"name": "MagnetometerOverRange", "enumType": "E1_GPS_BOOLEAN", "type": "U1", "default": "0", "value": 0, "members": {"GPS_FALSE": "0", "GPS_TRUE": "1"}}, {"name": "MinimumTemperatureAlarm", "enumType": "E1_GPS_BOOLEAN", "type": "U1", "default": "0", "value": 0, "members": {"GPS_FALSE": "0", "GPS_TRUE": "1"}}, {"name": "MaximumTemperatureAlarm", "enumType": "E1_GPS_BOOLEAN", "type": "U1", "default": "0", "value": 0, "members": {"GPS_FALSE": "0", "GPS_TRUE": "1"}}, {"name": "LowVoltageAlarm", "enumType": "E1_GPS_BOOLEAN", "type": "U1", "default": "0", "value": 0, "members": {"GPS_FALSE": "0", "GPS_TRUE": "1"}}, {"name": "HighVoltageAlarm", "enumType": "E1_GPS_BOOLEAN", "type": "U1", "default": "0", "value": 0, "members": {"GPS_FALSE": "0", "GPS_TRUE": "1"}}, {"name": "GnssAntennaFault", "enumType": "E1_GPS_BOOLEAN", "type": "U1", "default": "0", "value": 0, "members": {"GPS_FALSE": "0", "GPS_TRUE": "1"}}, {"name": "DataOutputOverflowAlarm", "enumType": "E1_GPS_BOOLEAN", "type": "U1", "default": "0", "value": 0, "members": {"GPS_FALSE": "0", "GPS_TRUE": "1"}}]}], "1570618370.7110512": [{"name": "GpsInterfaceState", "enumType": "E1_GPS_STATE", "type": "U1", "default": "GPS_OFFLINE", "value": 0, "members": {"GPS_OFFLINE": "0x00", "GPS_SETUP": "0x22", "GPS_OPERATIONAL": "0x25"}}, {"name": "GpsInterfaceMqttId", "type": "CH", "default": "0", "value": "BR12", "count": 48}, {"name": "GpsHighLevelStatus", "enumType": "E1_GPS_STATUS", "type": "U1", "default": "GPS_UNKNOWN", "value": 3, "members": {"GPS_PASS": "1", "GPS_DEGRADED": "2", "GPS_FAIL": "3", "GPS_UNKNOWN": "4"}}, {"name": "GpsLinkStatus", "type": "sGPS_LinkStatus", "members": [{"name": "BoundToUdpPort", "enumType": "E1_GPS_BOOLEAN", "type": "U1", "default": "0", "value": 1, "members": {"GPS_FALSE": "0", "GPS_TRUE": "1"}}, {"name": "MsgId29Present", "enumType": "E1_GPS_BOOLEAN", "type": "U1", "default": "0", "value": 0, "members": {"GPS_FALSE": "0", "GPS_TRUE": "1"}}, {"name": "MsgId23Present", "enumType": "E1_GPS_BOOLEAN", "type": "U1", "default": "0", "value": 0, "members": {"GPS_FALSE": "0", "GPS_TRUE": "1"}}]}, {"name": "GpsTime", "type": "sGPS_Time", "members": [{"name": "TimeValid", "enumType": "E1_GPS_BOOLEAN", "type": "U1", "default": "0", "value": 0, "members": {"GPS_FALSE": "0", "GPS_TRUE": "1"}}, {"name": "UnixTimestampSeconds", "type": "U4", "default": "0", "value": 0}, {"name": "Microseconds", "type": "U4", "default": "0", "value": 0}]}, {"name": "GpsPosition", "type": "sGPS_Position", "members": [{"name": "PositionValid", "enumType": "E1_GPS_BOOLEAN", "type": "U1", "default": "0", "value": 0, "members": {"GPS_FALSE": "0", "GPS_TRUE": "1"}}, {"name": "TypeOfFix", "enumType": "E1_GPS_GNSS_FIX_STATUS", "type": "U1", "default": "0", "value": 0, "members": {"GPS_NO_FIX": "0", "GPS_2D_FIX": "1", "GPS_3D_FIX": "2", "GPS_SBAS_GNSS_FIX": "3", "GPS_DIFFERENTIAL_GNSS_FIX": "4", "GPS_OMNISTAR_GNSS_FIX": "5", "GPS_RTK_FLOAT_GNSS_FIX": "6", "GPS_RTK_FIXED_GNSS_FIX": "7"}}, {"name": "HightMeters", "type": "F4", "default": "0", "value": 0.0}, {"name": "LatitudeDecimalDegrees", "type": "F4", "default": "0", "value": 0.0}, {"name": "LongitudeDecimalDegrees", "type": "F4", "default": "0", "value": 0.0}]}, {"name": "GpsHeading", "type": "sGPS_Heading", "members": [{"name": "HeadingValid", "enumType": "E1_GPS_BOOLEAN", "type": "U1", "default": "0", "value": 0, "members": {"GPS_FALSE": "0", "GPS_TRUE": "1"}}, {"name": "HeadingDegrees", "type": "F4", "default": "0", "value": 0.0}, {"name": "HeadingStandardDeviation", "type": "F4", "default": "0", "value": 0.0}]}, {"name": "GpsModuleStatus", "type": "sGPS_ModuleStatus", "members": [{"name": "SystemFailure", "enumType": "E1_GPS_BOOLEAN", "type": "U1", "default": "0", "value": 0, "members": {"GPS_FALSE": "0", "GPS_TRUE": "1"}}, {"name": "AccelerometerSensorFailure", "enumType": "E1_GPS_BOOLEAN", "type": "U1", "default": "0", "value": 0, "members": {"GPS_FALSE": "0", "GPS_TRUE": "1"}}, {"name": "GyroscopeSensorFailure", "enumType": "E1_GPS_BOOLEAN", "type": "U1", "default": "0", "value": 0, "members": {"GPS_FALSE": "0", "GPS_TRUE": "1"}}, {"name": "MagnetometerSensorFailure", "enumType": "E1_GPS_BOOLEAN", "type": "U1", "default": "0", "value": 0, "members": {"GPS_FALSE": "0", "GPS_TRUE": "1"}}, {"name": "SecondaryGnssFailure", "enumType": "E1_GPS_BOOLEAN", "type": "U1", "default": "0", "value": 0, "members": {"GPS_FALSE": "0", "GPS_TRUE": "1"}}, {"name": "PrimaryGnssFailure", "enumType": "E1_GPS_BOOLEAN", "type": "U1", "default": "0", "value": 0, "members": {"GPS_FALSE": "0", "GPS_TRUE": "1"}}, {"name": "AccelerometerOverRange", "enumType": "E1_GPS_BOOLEAN", "type": "U1", "default": "0", "value": 0, "members": {"GPS_FALSE": "0", "GPS_TRUE": "1"}}, {"name": "GyroscopeOverRange", "enumType": "E1_GPS_BOOLEAN", "type": "U1", "default": "0", "value": 0, "members": {"GPS_FALSE": "0", "GPS_TRUE": "1"}}, {"name": "MagnetometerOverRange", "enumType": "E1_GPS_BOOLEAN", "type": "U1", "default": "0", "value": 0, "members": {"GPS_FALSE": "0", "GPS_TRUE": "1"}}, {"name": "MinimumTemperatureAlarm", "enumType": "E1_GPS_BOOLEAN", "type": "U1", "default": "0", "value": 0, "members": {"GPS_FALSE": "0", "GPS_TRUE": "1"}}, {"name": "MaximumTemperatureAlarm", "enumType": "E1_GPS_BOOLEAN", "type": "U1", "default": "0", "value": 0, "members": {"GPS_FALSE": "0", "GPS_TRUE": "1"}}, {"name": "LowVoltageAlarm", "enumType": "E1_GPS_BOOLEAN", "type": "U1", "default": "0", "value": 0, "members": {"GPS_FALSE": "0", "GPS_TRUE": "1"}}, {"name": "HighVoltageAlarm", "enumType": "E1_GPS_BOOLEAN", "type": "U1", "default": "0", "value": 0, "members": {"GPS_FALSE": "0", "GPS_TRUE": "1"}}, {"name": "GnssAntennaFault", "enumType": "E1_GPS_BOOLEAN", "type": "U1", "default": "0", "value": 0, "members": {"GPS_FALSE": "0", "GPS_TRUE": "1"}}, {"name": "DataOutputOverflowAlarm", "enumType": "E1_GPS_BOOLEAN", "type": "U1", "default": "0", "value": 0, "members": {"GPS_FALSE": "0", "GPS_TRUE": "1"}}]}], "1570618371.7099447": [{"name": "GpsInterfaceState", "enumType": "E1_GPS_STATE", "type": "U1", "default": "GPS_OFFLINE", "value": 0, "members": {"GPS_OFFLINE": "0x00", "GPS_SETUP": "0x22", "GPS_OPERATIONAL": "0x25"}}, {"name": "GpsInterfaceMqttId", "type": "CH", "default": "0", "value": "BR12", "count": 48}, {"name": "GpsHighLevelStatus", "enumType": "E1_GPS_STATUS", "type": "U1", "default": "GPS_UNKNOWN", "value": 3, "members": {"GPS_PASS": "1", "GPS_DEGRADED": "2", "GPS_FAIL": "3", "GPS_UNKNOWN": "4"}}, {"name": "GpsLinkStatus", "type": "sGPS_LinkStatus", "members": [{"name": "BoundToUdpPort", "enumType": "E1_GPS_BOOLEAN", "type": "U1", "default": "0", "value": 1, "members": {"GPS_FALSE": "0", "GPS_TRUE": "1"}}, {"name": "MsgId29Present", "enumType": "E1_GPS_BOOLEAN", "type": "U1", "default": "0", "value": 0, "members": {"GPS_FALSE": "0", "GPS_TRUE": "1"}}, {"name": "MsgId23Present", "enumType": "E1_GPS_BOOLEAN", "type": "U1", "default": "0", "value": 0, "members": {"GPS_FALSE": "0", "GPS_TRUE": "1"}}]}, {"name": "GpsTime", "type": "sGPS_Time", "members": [{"name": "TimeValid", "enumType": "E1_GPS_BOOLEAN", "type": "U1", "default": "0", "value": 0, "members": {"GPS_FALSE": "0", "GPS_TRUE": "1"}}, {"name": "UnixTimestampSeconds", "type": "U4", "default": "0", "value": 0}, {"name": "Microseconds", "type": "U4", "default": "0", "value": 0}]}, {"name": "GpsPosition", "type": "sGPS_Position", "members": [{"name": "PositionValid", "enumType": "E1_GPS_BOOLEAN", "type": "U1", "default": "0", "value": 0, "members": {"GPS_FALSE": "0", "GPS_TRUE": "1"}}, {"name": "TypeOfFix", "enumType": "E1_GPS_GNSS_FIX_STATUS", "type": "U1", "default": "0", "value": 0, "members": {"GPS_NO_FIX": "0", "GPS_2D_FIX": "1", "GPS_3D_FIX": "2", "GPS_SBAS_GNSS_FIX": "3", "GPS_DIFFERENTIAL_GNSS_FIX": "4", "GPS_OMNISTAR_GNSS_FIX": "5", "GPS_RTK_FLOAT_GNSS_FIX": "6", "GPS_RTK_FIXED_GNSS_FIX": "7"}}, {"name": "HightMeters", "type": "F4", "default": "0", "value": 0.0}, {"name": "LatitudeDecimalDegrees", "type": "F4", "default": "0", "value": 0.0}, {"name": "LongitudeDecimalDegrees", "type": "F4", "default": "0", "value": 0.0}]}, {"name": "GpsHeading", "type": "sGPS_Heading", "members": [{"name": "HeadingValid", "enumType": "E1_GPS_BOOLEAN", "type": "U1", "default": "0", "value": 0, "members": {"GPS_FALSE": "0", "GPS_TRUE": "1"}}, {"name": "HeadingDegrees", "type": "F4", "default": "0", "value": 0.0}, {"name": "HeadingStandardDeviation", "type": "F4", "default": "0", "value": 0.0}]}, {"name": "GpsModuleStatus", "type": "sGPS_ModuleStatus", "members": [{"name": "SystemFailure", "enumType": "E1_GPS_BOOLEAN", "type": "U1", "default": "0", "value": 0, "members": {"GPS_FALSE": "0", "GPS_TRUE": "1"}}, {"name": "AccelerometerSensorFailure", "enumType": "E1_GPS_BOOLEAN", "type": "U1", "default": "0", "value": 0, "members": {"GPS_FALSE": "0", "GPS_TRUE": "1"}}, {"name": "GyroscopeSensorFailure", "enumType": "E1_GPS_BOOLEAN", "type": "U1", "default": "0", "value": 0, "members": {"GPS_FALSE": "0", "GPS_TRUE": "1"}}, {"name": "MagnetometerSensorFailure", "enumType": "E1_GPS_BOOLEAN", "type": "U1", "default": "0", "value": 0, "members": {"GPS_FALSE": "0", "GPS_TRUE": "1"}}, {"name": "SecondaryGnssFailure", "enumType": "E1_GPS_BOOLEAN", "type": "U1", "default": "0", "value": 0, "members": {"GPS_FALSE": "0", "GPS_TRUE": "1"}}, {"name": "PrimaryGnssFailure", "enumType": "E1_GPS_BOOLEAN", "type": "U1", "default": "0", "value": 0, "members": {"GPS_FALSE": "0", "GPS_TRUE": "1"}}, {"name": "AccelerometerOverRange", "enumType": "E1_GPS_BOOLEAN", "type": "U1", "default": "0", "value": 0, "members": {"GPS_FALSE": "0", "GPS_TRUE": "1"}}, {"name": "GyroscopeOverRange", "enumType": "E1_GPS_BOOLEAN", "type": "U1", "default": "0", "value": 0, "members": {"GPS_FALSE": "0", "GPS_TRUE": "1"}}, {"name": "MagnetometerOverRange", "enumType": "E1_GPS_BOOLEAN", "type": "U1", "default": "0", "value": 0, "members": {"GPS_FALSE": "0", "GPS_TRUE": "1"}}, {"name": "MinimumTemperatureAlarm", "enumType": "E1_GPS_BOOLEAN", "type": "U1", "default": "0", "value": 0, "members": {"GPS_FALSE": "0", "GPS_TRUE": "1"}}, {"name": "MaximumTemperatureAlarm", "enumType": "E1_GPS_BOOLEAN", "type": "U1", "default": "0", "value": 0, "members": {"GPS_FALSE": "0", "GPS_TRUE": "1"}}, {"name": "LowVoltageAlarm", "enumType": "E1_GPS_BOOLEAN", "type": "U1", "default": "0", "value": 0, "members": {"GPS_FALSE": "0", "GPS_TRUE": "1"}}, {"name": "HighVoltageAlarm", "enumType": "E1_GPS_BOOLEAN", "type": "U1", "default": "0", "value": 0, "members": {"GPS_FALSE": "0", "GPS_TRUE": "1"}}, {"name": "GnssAntennaFault", "enumType": "E1_GPS_BOOLEAN", "type": "U1", "default": "0", "value": 0, "members": {"GPS_FALSE": "0", "GPS_TRUE": "1"}}, {"name": "DataOutputOverflowAlarm", "enumType": "E1_GPS_BOOLEAN", "type": "U1", "default": "0", "value": 0, "members": {"GPS_FALSE": "0", "GPS_TRUE": "1"}}]}]}}}